LICENCE
MANIFEST.in
README.md
setup.cfg
setup.py
humanize/__init__.py
humanize/compat.py
humanize/filesize.py
humanize/i18n.py
humanize/number.py
humanize/time.py
humanize/locale/de_DE/LC_MESSAGES/humanize.mo
humanize/locale/de_DE/LC_MESSAGES/humanize.po
humanize/locale/fa_IR/LC_MESSAGES/humanize.mo
humanize/locale/fa_IR/LC_MESSAGES/humanize.po
humanize/locale/fi_FI/LC_MESSAGES/humanize.mo
humanize/locale/fi_FI/LC_MESSAGES/humanize.po
humanize/locale/fr_FR/LC_MESSAGES/humanize.mo
humanize/locale/fr_FR/LC_MESSAGES/humanize.po
humanize/locale/id_ID/LC_MESSAGES/humanize.mo
humanize/locale/id_ID/LC_MESSAGES/humanize.po
humanize/locale/ja_JP/LC_MESSAGES/humanize.mo
humanize/locale/ja_JP/LC_MESSAGES/humanize.po
humanize/locale/ko_KR/LC_MESSAGES/humanize.mo
humanize/locale/ko_KR/LC_MESSAGES/humanize.po
humanize/locale/nl_NL/LC_MESSAGES/humanize.mo
humanize/locale/nl_NL/LC_MESSAGES/humanize.po
humanize/locale/pt_BR/LC_MESSAGES/humanize.mo
humanize/locale/pt_BR/LC_MESSAGES/humanize.po
humanize/locale/ru_RU/LC_MESSAGES/humanize.mo
humanize/locale/ru_RU/LC_MESSAGES/humanize.po
humanize/locale/sk_SK/LC_MESSAGES/humanize.mo
humanize/locale/sk_SK/LC_MESSAGES/humanize.po
humanize/locale/tr_TR/LC_MESSAGES/humanize.mo
humanize/locale/tr_TR/LC_MESSAGES/humanize.po
humanize/locale/vi_VI/LC_MESSAGES/humanize.mo
humanize/locale/vi_VI/LC_MESSAGES/humanize.po
humanize/locale/zh_CN/LC_MESSAGES/humanize.mo
humanize/locale/zh_CN/LC_MESSAGES/humanize.po
lucky_humanize.egg-info/PKG-INFO
lucky_humanize.egg-info/SOURCES.txt
lucky_humanize.egg-info/dependency_links.txt
lucky_humanize.egg-info/entry_points.txt
lucky_humanize.egg-info/not-zip-safe
lucky_humanize.egg-info/top_level.txt