Metadata-Version: 1.1
Name: lucky-humanize
Version: 0.5.4.dev3
Summary: python humanize utilities
Home-page: http://github.com/luckydonald-forks/humanize
Author: Jason Moiron
Author-email: jmoiron@jmoiron.net
License: MIT
Keywords: humanize time size
Platform: UNKNOWN
Classifier: Development Status :: 4 - Beta
Classifier: Intended Audience :: Developers
Classifier: License :: OSI Approved :: MIT License
Classifier: Operating System :: POSIX
Classifier: Programming Language :: Python :: 3
Classifier: Programming Language :: Python
